puup/__init__.py
puup/cli.py
puup/dump.py
puup/entropy.py
puup/lazy.py
puup/render.py
puup/template.py
puup/words.py
puup/data/Makefile
puup/data/__init__.py
puup/data/a.py
puup/data/n.py
puup/data/p.py
puup/data/r.py
puup/data/s.py
puup/data/v.py
puup/data/wn.py
puup/data/wp.py
puup-0.1.2.dist-info/entry_points.txt
puup-0.1.2.dist-info/LICENSE
puup-0.1.2.dist-info/WHEEL
puup-0.1.2.dist-info/METADATA
puup-0.1.2.dist-info/RECORD
