Metadata-Version: 2.1
Name: puup
Version: 0.1.2
Summary: Potentially Universally Unique Phrase generator
Author-email: Chris Coleman <chris@chriscoleman.uk>
Classifier: License :: OSI Approved :: MIT License
Requires-Dist: click
Requires-Dist: confuse
